piex/__init__.py
piex/explorer.py
piex/scoring.py
piex-0.2.0.dist-info/AUTHORS.rst
piex-0.2.0.dist-info/LICENSE
piex-0.2.0.dist-info/METADATA
piex-0.2.0.dist-info/WHEEL
piex-0.2.0.dist-info/top_level.txt
piex-0.2.0.dist-info/RECORD
