Metadata-Version: 2.1
Name: piex
Version: 0.2.0
Summary: Pipeline Explorer
Home-page: https://github.com/HDI-Project/piex
Author: MIT Data To AI Lab
Author-email: dailabmit@gmail.com
License: MIT license
Keywords: piex
Platform: UNKNOWN
Classifier: Development Status :: 2 - Pre-Alpha
Classifier: Intended Audience :: Developers
Classifier: License :: OSI Approved :: MIT License
Classifier: Natural Language :: English
Classifier: Programming Language :: Python :: 3
Classifier: Programming Language :: Python :: 3.5
Classifier: Programming Language :: Python :: 3.6
Classifier: Programming Language :: Python :: 3.7
Requires-Python: >=3.4
Requires-Dist: boto3 (==1.9.27)
Requires-Dist: numpy (==1.15.2)
Requires-Dist: mit-d3m (==0.1.1)
Requires-Dist: mlblocks (==0.2.3)
Requires-Dist: mlprimitives (==0.1.3)
Requires-Dist: pandas (==0.23.4)
Requires-Dist: pymongo (==3.7.2)
Requires-Dist: scikit-learn (==0.20.0)
Requires-Dist: scipy (==1.1.0)
Provides-Extra: demo
Requires-Dist: jupyter (==1.0.0) ; extra == 'demo'
Provides-Extra: dev
Requires-Dist: jupyter (==1.0.0) ; extra == 'dev'
Requires-Dist: bumpversion (>=0.5.3) ; extra == 'dev'
Requires-Dist: pip (>=9.0.1) ; extra == 'dev'
Requires-Dist: watchdog (>=0.8.3) ; extra == 'dev'
Requires-Dist: m2r (>=0.2.0) ; extra == 'dev'
Requires-Dist: Sphinx (>=1.7.1) ; extra == 'dev'
Requires-Dist: sphinx-rtd-theme (>=0.2.4) ; extra == 'dev'
Requires-Dist: flake8 (>=3.5.0) ; extra == 'dev'
Requires-Dist: isort (>=4.3.4) ; extra == 'dev'
Requires-Dist: autoflake (>=1.1) ; extra == 'dev'
Requires-Dist: autopep8 (>=1.3.5) ; extra == 'dev'
Requires-Dist: twine (>=1.10.0) ; extra == 'dev'
Requires-Dist: wheel (>=0.30.0) ; extra == 'dev'
Requires-Dist: coverage (>=4.5.1) ; extra == 'dev'
Requires-Dist: pytest (>=3.4.2) ; extra == 'dev'
Requires-Dist: tox (>=2.9.1) ; extra == 'dev'
Provides-Extra: test
Requires-Dist: coverage (>=4.5.1) ; extra == 'test'
Requires-Dist: pytest (>=3.4.2) ; extra == 'test'
Requires-Dist: tox (>=2.9.1) ; extra == 'test'
